causal_assistant/__init__.py
causal_assistant/helper.py
causal_assistant/main.py
causal_assistant/utils.py
causal_assistant-0.3.0.dist-info/METADATA
causal_assistant-0.3.0.dist-info/WHEEL
causal_assistant-0.3.0.dist-info/licenses/LICENSE
causal_assistant-0.3.0.dist-info/RECORD
