Metadata-Version: 2.4
Name: causal-assistant
Version: 0.3.0
Summary: Causal Bootstrapping utility package
Project-URL: Homepage, https://github.com/nathancartlidge/causal_assistant
Project-URL: Bug Tracker, https://github.com/nathancartlidge/causal_assistant/issues
Author-email: Nathan Cartlidge <nac120@student.bham.ac.uk>, Jianqiao Mao <jxm1417@student.bham.ac.uk>
License-Expression: GPL-3.0
License-File: LICENSE
Classifier: Development Status :: 4 - Beta
Classifier: Intended Audience :: Developers
Classifier: Intended Audience :: Science/Research
Classifier: License :: OSI Approved :: GNU General Public License v3 (GPLv3)
Classifier: Operating System :: OS Independent
Classifier: Programming Language :: Python :: 3
Classifier: Programming Language :: Python :: 3.12
Classifier: Topic :: Scientific/Engineering
Requires-Python: >=3.12
Requires-Dist: causalbootstrapping>=0.1.5
Requires-Dist: matplotlib>=3.10.1
Requires-Dist: numpy>=1.26.4
Requires-Dist: pandas>=2.2.3
Requires-Dist: scikit-learn>=1.5.2
Requires-Dist: sympy>=1.13.3
